d1_library/__init__.py
d1_library/sql_tools/__init__.py
d1_library/sql_tools/db_fetcher.py
d1_library/sql_tools/db_insert.py
d1_library/sql_tools/sql_scripts/daily_data.sql
d1_library/sql_tools/sql_scripts/daily_spec_data.sql
d1_library/sql_tools/sql_scripts/exchange_id.sql
d1_library/sql_tools/sql_scripts/insert_daily_data.sql
d1_library/sql_tools/sql_scripts/insert_symbols.sql
d1_library/sql_tools/sql_scripts/symbol_id.sql
d1_library/sql_tools/sql_scripts/symbols.sql
d1_library/sql_tools/sql_scripts/vendor_id.sql
d1_library/stock_parser/__init__.py
d1_library/stock_parser/fmp_fetcher.py
d1_library/stock_parser/rapid_fetcher.py
d1_library/stock_parser/stock_list_fetcher.py
d1_library/stock_parser/tdameritrade_fetcher.py
d1_library/stock_parser/yahoo_fetcher.py
d1_library/strategies/__init__.py
d1_library/strategies/momentum.py
d1_library/strategies/portfolio.py
d1_library/telegram_bot/__init__.py
d1_library/telegram_bot/notificationsender.py
d1_library/terminal/__init__.py
d1_library/terminal/alpaca.py
d1_library/terminal/ibkr.py
d1_library-1.0.0.dist-info/METADATA
d1_library-1.0.0.dist-info/WHEEL
d1_library-1.0.0.dist-info/top_level.txt
d1_library-1.0.0.dist-info/RECORD
