Metadata-Version: 2.2
Name: d1_library
Version: 1.0.0
Summary: D-one Trading Platform Library
Home-page: https://github.com/reraaaaa/D-one-Trading-Platform
Author: D-one
Author-email: D-one <your.email@example.com>
Project-URL: Homepage, https://github.com/reraaaaa/D-one-Trading-Platform
Project-URL: Repository, https://github.com/reraaaaa/D-one-Trading-Platform.git
Classifier: Development Status :: 3 - Alpha
Classifier: Intended Audience :: Developers
Classifier: License :: OSI Approved :: MIT License
Classifier: Programming Language :: Python :: 3
Classifier: Programming Language :: Python :: 3.8
Classifier: Programming Language :: Python :: 3.9
Classifier: Programming Language :: Python :: 3.10
Classifier: Programming Language :: Python :: 3.11
Classifier: Programming Language :: Python :: 3.12
Requires-Python: >=3.8,<3.13
Requires-Dist: numpy>=1.26.0
Requires-Dist: pandas>=2.1.0
Requires-Dist: pytz>=2022.6
Requires-Dist: requests>=2.31.0
Requires-Dist: scipy>=1.11.0
Requires-Dist: SQLAlchemy>=1.4.44
Requires-Dist: fmp-python>=0.1.4
Requires-Dist: cvxpy>=1.4.2
Requires-Dist: yfinance>=0.2.33
Requires-Dist: PyPortfolioOpt>=1.5.5
Requires-Dist: alpha_vantage>=2.3.1
Requires-Dist: psycopg2-binary>=2.9.5
Requires-Dist: python-dotenv>=0.19.0
Requires-Dist: ib-insync>=0.9.86
Dynamic: author
Dynamic: home-page
Dynamic: requires-python
